simulator/__init__.py
simulator/_version.py
simulator/main.py
simulator/api/__init__.py
simulator/api/device_creation_metadata_api.py
simulator/api/firmware_version_api.py
simulator/auth/__init__.py
simulator/auth/oauth2_client.py
simulator/auth/oauth_flow.py
simulator/commands/__init__.py
simulator/commands/command_handler.py
simulator/config/__init__.py
simulator/config/config_manager.py
simulator/config/schemas.py
simulator/config/templates/config.template.json
simulator/connectivity/__init__.py
simulator/connectivity/iot_hub_client.py
simulator/device_setup/__init__.py
simulator/device_setup/configuration_ui.py
simulator/device_setup/device_selector.py
simulator/device_setup/setup_coordinator.py
simulator/provisioning/__init__.py
simulator/provisioning/device_provisioner.py
simulator/telemetry/__init__.py
simulator/telemetry/sender.py
simulator/telemetry/telemetry_generator.py
simulator/telemetry/message_generators/__init__.py
simulator/telemetry/message_generators/alerts_generator.py
simulator/telemetry/message_generators/base_message_generator.py
simulator/telemetry/message_generators/fw_debug_generator.py
simulator/telemetry/message_generators/measurement_generator.py
simulator/telemetry/message_generators/state_generator.py
simulator/twin/__init__.py
simulator/twin/default_config_applier.py
simulator/twin/firmware_reporter.py
simulator/twin/reported_store.py
simulator/twin/twin_manager.py
simulator/utils/__init__.py
simulator/utils/logger.py
simulator/utils/version_parser.py
simulator/utils/schema/__init__.py
simulator/utils/schema/schema_generator.py
simulator/utils/schema/schema_reference_resolver.py
simulator/utils/schema/schema_value_generator.py
tgiot_device_simulator-1.0.0.5.dist-info/METADATA
tgiot_device_simulator-1.0.0.5.dist-info/WHEEL
tgiot_device_simulator-1.0.0.5.dist-info/entry_points.txt
tgiot_device_simulator-1.0.0.5.dist-info/top_level.txt
tgiot_device_simulator-1.0.0.5.dist-info/RECORD
