Metadata-Version: 2.4
Name: tgiot-device-simulator
Version: 1.0.0.5
Summary: A comprehensive IoT device simulator for Azure IoT Hub and IoT Platform servers
Author-email: IoT Platform Team <iot-platform@example.com>
License-Expression: MIT
Project-URL: Homepage, https://tandemg.com
Keywords: iot,azure,simulator,device,telemetry
Classifier: Development Status :: 4 - Beta
Classifier: Intended Audience :: Developers
Classifier: Programming Language :: Python :: 3
Classifier: Programming Language :: Python :: 3.9
Classifier: Programming Language :: Python :: 3.10
Classifier: Programming Language :: Python :: 3.11
Classifier: Programming Language :: Python :: 3.12
Classifier: Programming Language :: Python :: 3.13
Classifier: Topic :: Software Development :: Libraries :: Python Modules
Classifier: Topic :: Internet :: WWW/HTTP :: HTTP Servers
Classifier: Topic :: Scientific/Engineering :: Interface Engine/Protocol Translator
Requires-Python: >=3.9
Requires-Dist: azure-iot-device>=2.12.0
Requires-Dist: aiohttp>=3.10.0
Requires-Dist: rich>=13.6.0
Requires-Dist: pydantic>=2.12.0
Requires-Dist: authlib>=1.2.0
Requires-Dist: faker>=26.0.0
Provides-Extra: dev
Requires-Dist: pytest>=7.4.0; extra == "dev"
Requires-Dist: pytest-asyncio>=0.21.0; extra == "dev"
Requires-Dist: pytest-cov>=4.1.0; extra == "dev"
Requires-Dist: ruff>=0.1.0; extra == "dev"
Requires-Dist: mypy>=1.6.0; extra == "dev"
Provides-Extra: test
Requires-Dist: pytest>=7.4.0; extra == "test"
Requires-Dist: pytest-asyncio>=0.21.0; extra == "test"
Requires-Dist: pytest-cov>=4.1.0; extra == "test"
Provides-Extra: lint
Requires-Dist: ruff>=0.1.0; extra == "lint"
Requires-Dist: mypy>=1.6.0; extra == "lint"
